Kahi-0.1.1a0.data/scripts/kahi_generate
Kahi-0.1.1a0.data/scripts/kahi_run
kahi/Kahi.py
kahi/KahiBase.py
kahi/PluginGenerator.py
kahi/__init__.py
kahi/_version.py
kahi/templates/__init__.py
kahi/templates/plugin/Kahi_template/MANIFEST.in
kahi/templates/plugin/Kahi_template/README.md
kahi/templates/plugin/Kahi_template/setup.py
kahi/templates/plugin/Kahi_template/kahi_template/Kahi_template.py
kahi/templates/plugin/Kahi_template/kahi_template/__init__.py
kahi/templates/plugin/Kahi_template/kahi_template/_version.py
Kahi-0.1.1a0.dist-info/LICENSE
Kahi-0.1.1a0.dist-info/METADATA
Kahi-0.1.1a0.dist-info/WHEEL
Kahi-0.1.1a0.dist-info/top_level.txt
Kahi-0.1.1a0.dist-info/RECORD
