Metadata-Version: 2.1
Name: Kahi
Version: 0.1.1a0
Summary: ETL (Extract, Transform and Load) for bibliographic data using an advance data workflow
Home-page: https://github.com/colav/Kahi
Author: Colav
Author-email: colav@udea.edu.co
License: BSD
License-File: LICENSE
Requires-Dist: pyyaml
Requires-Dist: pymongo
Provides-Extra: all
Requires-Dist: kahi-doaj-sources; extra == "all"
Requires-Dist: kahi-minciencias-opendata-affiliations; extra == "all"
Requires-Dist: kahi-minciencias-opendata-person; extra == "all"
Requires-Dist: kahi-openalex-affiliations; extra == "all"
Requires-Dist: kahi-openalex-person; extra == "all"
Requires-Dist: kahi-openalex-sources; extra == "all"
Requires-Dist: kahi-openalex-subjects; extra == "all"
Requires-Dist: kahi-openalex-works; extra == "all"
Requires-Dist: kahi-ranking-udea-works; extra == "all"
Requires-Dist: kahi-ror-affiliations; extra == "all"
Requires-Dist: kahi-scholar-works; extra == "all"
Requires-Dist: kahi-scienti-affiliations; extra == "all"
Requires-Dist: kahi-scienti-person; extra == "all"
Requires-Dist: kahi-scienti-sources; extra == "all"
Requires-Dist: kahi-scimago-sources; extra == "all"
Requires-Dist: kahi-scopus-works; extra == "all"
Requires-Dist: kahi-staff-udea-affiliations; extra == "all"
Requires-Dist: kahi-staff-udea-person; extra == "all"
Requires-Dist: kahi-wos-works; extra == "all"
